{
    "training start": "2021-05-22 13:57",
    "duration": 89.03315515915553,
    "initial balance": 10000,
    "training episodes": 5000,
    "training batch size": 500,
    "lookback window size": 100,
    "depth": 7,
    "lr": 0.0001,
    "epochs": 15,
    "batch size": 64,
    "normalize value": 64000,
    "model": "CNN",
    "comment": "Normalized",
    "saving time": "2021-05-22 14:03",
    "Actor name": "10443.86_Crypto_trader_Actor.h5",
    "Critic name": "10443.86_Crypto_trader_Critic.h5",
    "Actor Nodes": [
        64,
        64,
        64
    ],
    "Critic Nodes": [
        64,
        64,
        64
    ],
    "Indicators": [
        "RSI"
    ]
}